{"ovbqgijx":{"additionalInfo":"Ռեստորանի սեփականատեր ես","baggage":"Հաքագազ","bio":"կին, 73","illness":"Սրտի արատ","phobia":"Վիրահատություն","profession":"QA","username":"Արսեն"},"xbowypsq":{"additionalInfo":"Ունես կոպեկների հավաքածու","baggage":"Գոտի","bio":"կին, 93","illness":"Կատարախտ","phobia":"Փոքր իրեր","profession":"Կոշկակար","username":"Հարութ"},"txyextag":{"additionalInfo":"Տիրապետում է 7 լեզվի","baggage":"Դիմակ բժշկական 50 հատ","bio":"տղամարդ, 39","illness":"Լեզվի արատավորում","phobia":"Թռչուն","profession":"Սպորտսմեն","username":"Լիան"},"srumsluh":{"additionalInfo":"Ժող-ն ես ավարտել","baggage":"10 հատ ձու","bio":"տղամարդ, 79","illness":"Աստմա","phobia":"Մանր անցքեր","profession":"Լրագրող","username":"Ռաֆֆի"},"gwfkkvbr":{"additionalInfo":"Եղել ես եվրոպայի 15 երկրներում","baggage":"Հնդկական համեմունքներ","bio":"տղամարդ, 16","illness":"Մաշկի քաղցկեղ","phobia":"Ասեղ","profession":"Նախագահ","username":""}}